README.md
setup.py
django_timeseries_tables/__init__.py
django_timeseries_tables/base.py
django_timeseries_tables/fields.py
django_timeseries_tables/internal_models.py
django_timeseries_tables/models.py
django_timeseries_tables/query_set.py
django_timeseries_tables.egg-info/PKG-INFO
django_timeseries_tables.egg-info/SOURCES.txt
django_timeseries_tables.egg-info/dependency_links.txt
django_timeseries_tables.egg-info/not-zip-safe
django_timeseries_tables.egg-info/requires.txt
django_timeseries_tables.egg-info/top_level.txt