Metadata-Version: 1.2
Name: django-timeseries-tables
Version: 0.1.2
Summary: Django timeseries models
Home-page: https://github.com/jazzband/django-model-utils/
Author: Andrew Webb
Author-email: androbwebb@gmail.com
Maintainer: AndRobWebb
License: BSD
Platform: UNKNOWN
Classifier: Environment :: Web Environment
Classifier: Intended Audience :: Developers
Classifier: License :: OSI Approved :: BSD License
Classifier: Operating System :: OS Independent
Classifier: Programming Language :: Python
Classifier: Programming Language :: Python :: 3.6
Classifier: Framework :: Django
Classifier: Framework :: Django :: 1.8
Classifier: Framework :: Django :: 1.9
Classifier: Framework :: Django :: 1.10
Classifier: Framework :: Django :: 1.11
Classifier: Framework :: Django :: 2.0
